Workbook

Sheet README
B2: Risk Assessment Model — Extended Version
B5: Sheet | C5: What it contains
B6: Model Params | C6: Editable weights, caps and risk thresholds (yellow = edit here). Every formula in the workbook references these cells.
B7: Credit Risk | C7: Four personas' inputs, plus the ORIGINAL model (matches the Forage calculator) and a CORRECTED model side by side, with the flaw explained.
B8: Sensitivity | C8: One-at-a-time sensitivity analysis: how far each input alone would need to move to flip a persona's risk category.
B9: Real Estate Risk | C9: Quantified version of the Florida apartment-complex scenario: probability x impact, mitigation strategy, and mitigation cost vs. exposure.
B11: The flaw in the original model
B12: The Forage calculator adds every normalized factor into the weighted score, including Debt and Late Payments. Because the score is read as 'higher = safer', that means more debt and more missed payments PUSH THE SCORE UP — the opposite of what should happen. The Corrected model inverts those two factors (100 - value) before weighting them. Categories barely move for these four personas, but the ranking and the score gap to the next category boundary both change.
B14: Color legend
B15: Blue text | C15: Hardcoded input — safe to edit
B16: Black text | C16: Formula — do not overwrite
B17: Yellow fill | C17: Key assumption / model parameter

Sheet Model Params
B2: Model Parameters
B3: Edit the yellow cells to re-run the whole model with different weights or thresholds.
B5: Parameter | C5: Value
B6: Credit score weight | C6: 0.25
B7: Annual income weight | C7: 0.2
B8: Debt weight | C8: 0.2
B9: Savings weight | C9: 0.25
B10: Late payments weight | C10: 0.1
B11: Weights sum to | C11: =C6+C7+C8+C9+C10 -> 1
B13: Credit score scale — min | C13: 300
B14: Credit score scale — max | C14: 850
B15: Income cap ($, normalization ceiling) | C15: 300000
B16: Debt cap ($, normalization ceiling) | C16: 300000
B17: Savings cap ($, normalization ceiling) | C17: 500000
B18: Late payments cap (count) | C18: 5
B20: High Risk if score <= | C20: 33
B21: Medium Risk if score <= | C21: 66

Sheet Credit Risk
B2: Credit Risk — Original vs. Corrected Model
B4: Inputs
A5: Risk Attribute | B5: Persona 1 | C5: Persona 2 | D5: Persona 3 | E5: Persona 4
A6: Annual Income ($) | B6: 280000 | C6: 180000 | D6: 100000 | E6: 150000
A7: Credit Score | B7: 760 | C7: 700 | D7: 660 | E7: 720
A8: Debt ($) | B8: 150000 | C8: 100000 | D8: 90000 | E8: 200000
A9: Savings ($) | B9: 450000 | C9: 120000 | D9: 20000 | E9: 80000
A10: Late Payments | B10: 0 | C10: 1 | D10: 2 | E10: 1
B12: Normalized factors (0-100 scale)
A13: Factor | B13: Persona 1 | C13: Persona 2 | D13: Persona 3 | E13: Persona 4
A14: Credit Score (N) | B14: =(B7-'Model Params'!$C$13)/('Model Params'!$C$14-'Model Params'!$C$13)*100 -> 83.636364 | C14: =(C7-'Model Params'!$C$13)/('Model Params'!$C$14-'Model Params'!$C$13)*100 -> 72.727273 | D14: =(D7-'Model Params'!$C$13)/('Model Params'!$C$14-'Model Params'!$C$13)*100 -> 65.454545 | E14: =(E7-'Model Params'!$C$13)/('Model Params'!$C$14-'Model Params'!$C$13)*100 -> 76.363636
A15: Annual Income (N) | B15: =MIN(B6/'Model Params'!$C$15,1)*100 -> 93.333333 | C15: =MIN(C6/'Model Params'!$C$15,1)*100 -> 60 | D15: =MIN(D6/'Model Params'!$C$15,1)*100 -> 33.333333 | E15: =MIN(E6/'Model Params'!$C$15,1)*100 -> 50
A16: Debt (N, raw) | B16: =MIN(B8/'Model Params'!$C$16,1)*100 -> 50 | C16: =MIN(C8/'Model Params'!$C$16,1)*100 -> 33.333333 | D16: =MIN(D8/'Model Params'!$C$16,1)*100 -> 30 | E16: =MIN(E8/'Model Params'!$C$16,1)*100 -> 66.666667
A17: Savings (N) | B17: =MIN(B9/'Model Params'!$C$17,1)*100 -> 90 | C17: =MIN(C9/'Model Params'!$C$17,1)*100 -> 24 | D17: =MIN(D9/'Model Params'!$C$17,1)*100 -> 4 | E17: =MIN(E9/'Model Params'!$C$17,1)*100 -> 16
A18: Late Payments (N, raw) | B18: =MIN(B10/'Model Params'!$C$18,1)*100 -> 0 | C18: =MIN(C10/'Model Params'!$C$18,1)*100 -> 20 | D18: =MIN(D10/'Model Params'!$C$18,1)*100 -> 40 | E18: =MIN(E10/'Model Params'!$C$18,1)*100 -> 20
B20: Scores & categories
B21: Persona 1 | C21: Persona 2 | D21: Persona 3 | E21: Persona 4
A22: Weighted Score — ORIGINAL | B22: =B14*'Model Params'!$C$6+B15*'Model Params'!$C$7+B16*'Model Params'!$C$8+B17*'Model Params'!$C$9+B18*'Model Params'!$C$10 -> 72.075758 | C22: =C14*'Model Params'!$C$6+C15*'Model Params'!$C$7+C16*'Model Params'!$C$8+C17*'Model Params'!$C$9+C18*'Model Params'!$C$10 -> 44.848485 | D22: =D14*'Model Params'!$C$6+D15*'Model Params'!$C$7+D16*'Model Params'!$C$8+D17*'Model Params'!$C$9+D18*'Model Params'!$C$10 -> 34.030303 | E22: =E14*'Model Params'!$C$6+E15*'Model Params'!$C$7+E16*'Model Params'!$C$8+E17*'Model Params'!$C$9+E18*'Model Params'!$C$10 -> 48.424242
A23: Category — ORIGINAL | B23: =IF(B22<='Model Params'!$C$20,"High Risk",IF(B22<='Model Params'!$C$21,"Medium Risk","Low Risk")) -> Low Risk | C23: =IF(C22<='Model Params'!$C$20,"High Risk",IF(C22<='Model Params'!$C$21,"Medium Risk","Low Risk")) -> Medium Risk | D23: =IF(D22<='Model Params'!$C$20,"High Risk",IF(D22<='Model Params'!$C$21,"Medium Risk","Low Risk")) -> Medium Risk | E23: =IF(E22<='Model Params'!$C$20,"High Risk",IF(E22<='Model Params'!$C$21,"Medium Risk","Low Risk")) -> Medium Risk
A24: Weighted Score — CORRECTED | B24: =B14*'Model Params'!$C$6+B15*'Model Params'!$C$7+(100-B16)*'Model Params'!$C$8+B17*'Model Params'!$C$9+(100-B18)*'Model Params'!$C$10 -> 82.075758 | C24: =C14*'Model Params'!$C$6+C15*'Model Params'!$C$7+(100-C16)*'Model Params'!$C$8+C17*'Model Params'!$C$9+(100-C18)*'Model Params'!$C$10 -> 57.515152 | D24: =D14*'Model Params'!$C$6+D15*'Model Params'!$C$7+(100-D16)*'Model Params'!$C$8+D17*'Model Params'!$C$9+(100-D18)*'Model Params'!$C$10 -> 44.030303 | E24: =E14*'Model Params'!$C$6+E15*'Model Params'!$C$7+(100-E16)*'Model Params'!$C$8+E17*'Model Params'!$C$9+(100-E18)*'Model Params'!$C$10 -> 47.757576
A25: Category — CORRECTED | B25: =IF(B24<='Model Params'!$C$20,"High Risk",IF(B24<='Model Params'!$C$21,"Medium Risk","Low Risk")) -> Low Risk | C25: =IF(C24<='Model Params'!$C$20,"High Risk",IF(C24<='Model Params'!$C$21,"Medium Risk","Low Risk")) -> Medium Risk | D25: =IF(D24<='Model Params'!$C$20,"High Risk",IF(D24<='Model Params'!$C$21,"Medium Risk","Low Risk")) -> Medium Risk | E25: =IF(E24<='Model Params'!$C$20,"High Risk",IF(E24<='Model Params'!$C$21,"Medium Risk","Low Risk")) -> Medium Risk
A26: Points to nearest boundary (corrected) | B26: =IF(B24<='Model Params'!$C$20,'Model Params'!$C$20-B24,IF(B24<='Model Params'!$C$21,MIN(B24-'Model Params'!$C$20,'Model Params'!$C$21-B24),B24-'Model Params'!$C$21)) -> 16.075758 | C26: =IF(C24<='Model Params'!$C$20,'Model Params'!$C$20-C24,IF(C24<='Model Params'!$C$21,MIN(C24-'Model Params'!$C$20,'Model Params'!$C$21-C24),C24-'Model Params'!$C$21)) -> 8.4848485 | D26: =IF(D24<='Model Params'!$C$20,'Model Params'!$C$20-D24,IF(D24<='Model Params'!$C$21,MIN(D24-'Model Params'!$C$20,'Model Params'!$C$21-D24),D24-'Model Params'!$C$21)) -> 11.030303 | E26: =IF(E24<='Model Params'!$C$20,'Model Params'!$C$20-E24,IF(E24<='Model Params'!$C$21,MIN(E24-'Model Params'!$C$20,'Model Params'!$C$21-E24),E24-'Model Params'!$C$21)) -> 14.757576
A28: Note: the ORIGINAL model matches the Forage risk calculator exactly. The CORRECTED model inverts Debt and Late Payments (100 - value) so more debt and more missed payments lower the score, as they should. See README for detail.

Sheet Sensitivity
B2: Sensitivity Analysis — One Factor at a Time (Corrected Model)
B3: For each persona, each input is shifted up and down alone (others held at baseline) to see how far it would need to move to flip the risk category. 'No flip in range' means the tested range (±50% financials, ±100 credit points, 0–5 late payments) was not enough by itself.
A5: Persona | B5: Input | C5: Baseline Score | D5: Baseline Category | E5: Direction Tested | F5: Range Tested | G5: Would it flip the category?
A6: Persona 1 | B6: All 5 inputs | C6: 82.08 | D6: Low Risk | E6: up/down | F6: ±50% financial / ±100 credit pts / 0-5 late | G6: No flip in range — comfortably inside Low Risk
A7: Persona 2 | B7: All 5 inputs | C7: 57.52 | D7: Medium Risk | E7: up/down | F7: ±50% financial / ±100 credit pts / 0-5 late | G7: No flip in range on any single input
A8: Persona 3 | B8: All 5 inputs | C8: 44.03 | D8: Medium Risk | E8: up/down | F8: ±50% financial / ±100 credit pts / 0-5 late | G8: No flip in range — needs multiple inputs to move together
A9: Persona 4 | B9: All 5 inputs | C9: 47.76 | D9: Medium Risk | E9: up/down | F9: ±50% financial / ±100 credit pts / 0-5 late | G9: No flip in range on any single input
B11: Key takeaway: within realistic ranges, no single input alone is strong enough to move any persona into a different risk category — the model requires several factors to move together. Persona 3 sits closest to a boundary (11.03 points above the High Risk line), so it's the most sensitive to a combined shock, e.g. one more late payment together with a modest income drop. The full 200-scenario grid behind this summary is in sensitivity_scenarios.csv / the SQL sensitivity script.

Sheet Real Estate Risk
B2: Real Estate Risk Register — Florida Apartment Complex
B3: Quantified version of the Risk Mitigation Workbook scenario. Probability and impact are this project's own assumptions (see column H), not Goldman Sachs data.
A5: Risk | B5: Probability | C5: Impact if it occurs ($) | D5: Expected Annual Loss ($) | E5: Risk Score | F5: Category | G5: Mitigation Strategy | H5: Mitigation Cost ($/yr) | I5: Mitigation Cost as % of EAL | J5: Assumption / Rationale
A6: Hurricane / storm damage | B6: 0.15 | C6: 900000 | D6: =B6*C6 -> 135000 | E6: =D6/10000 -> 13.5 | F6: =IF(E6<=10,"Low Risk",IF(E6<=25,"Medium Risk","High Risk")) -> Medium Risk | G6: Windstorm insurance rider + annual roof/drainage inspection | H6: 45000 | I6: =H6/D6 -> 0.33333333 | J6: Florida coastal exposure; low-frequency, very high-severity event
A7: Property tax increase | B7: 0.4 | C7: 120000 | D7: =B7*C7 -> 48000 | E7: =D7/10000 -> 4.8 | F7: =IF(E7<=10,"Low Risk",IF(E7<=25,"Medium Risk","High Risk")) -> Low Risk | G7: Annual reassessment review with a property tax attorney | H7: 8000 | I7: =H7/D7 -> 0.16666667 | J7: Moderately likely given rising FL valuations; moderate impact
A8: Occupancy drop from new competing complexes | B8: 0.35 | C8: 250000 | D8: =B8*C8 -> 87500 | E8: =D8/10000 -> 8.75 | F8: =IF(E8<=10,"Low Risk",IF(E8<=25,"Medium Risk","High Risk")) -> Low Risk | G8: Tenant retention incentives + accelerate amenity upgrades | H8: 60000 | I8: =H8/D8 -> 0.68571429 | J8: New supply visible in the local pipeline; direct hit to rental income
A9: Seasonal occupancy swings | B9: 0.6 | C9: 90000 | D9: =B9*C9 -> 54000 | E9: =D9/10000 -> 5.4 | F9: =IF(E9<=10,"Low Risk",IF(E9<=25,"Medium Risk","High Risk")) -> Low Risk | G9: Flexible/short-term lease mix to smooth off-season vacancy | H9: 15000 | I9: =H9/D9 -> 0.27777778 | J9: Near-certain annually in FL rental markets; comparatively small impact
A10: Major unplanned repair (non-storm) | B10: 0.25 | C10: 150000 | D10: =B10*C10 -> 37500 | E10: =D10/10000 -> 3.75 | F10: =IF(E10<=10,"Low Risk",IF(E10<=25,"Medium Risk","High Risk")) -> Low Risk | G10: Capital reserve fund from NOI + preventive maintenance plan | H10: 20000 | I10: =H10/D10 -> 0.53333333 | J10: Aging-building risk; reserve funding is cheaper than reactive repair
A12: TOTAL | D12: =SUM(D6:D10) -> 362000 | H12: =SUM(H6:H10) -> 148000
A13: Net exposure after mitigation cost | D13: =D12-H12 -> 214000
